{
  "name": "Medical Technology",
  "slug": "medical_technology",
  "sector": "Healthcare",
  "sector_slug": "healthcare",
  "description": "Medical laboratory technology, diagnostic imaging, and biomedical equipment",
  "questions": [
    {"question_text": "Describe the quality control procedures you follow in a clinical laboratory.", "question_type": "technical", "difficulty": "medium", "expected_answer": "Daily QC, Levey-Jennings charts, Westgard rules, proficiency testing", "keywords": ["quality control", "Westgard", "proficiency testing"]},
    {"question_text": "How do you handle critical lab values and what is the reporting protocol?", "question_type": "situational", "difficulty": "medium", "expected_answer": "Immediate notification, verification, documentation, read-back", "keywords": ["critical values", "notification", "patient safety"]},
    {"question_text": "Explain the principles behind PCR testing.", "question_type": "technical", "difficulty": "hard", "expected_answer": "DNA amplification, denaturation, annealing, extension, clinical applications", "keywords": ["PCR", "molecular diagnostics", "DNA"]},
    {"question_text": "How do you troubleshoot an automated analyzer that produces unexpected results?", "question_type": "situational", "difficulty": "hard", "expected_answer": "Systematic approach: controls, calibration, reagents, maintenance logs", "keywords": ["troubleshooting", "analyzer", "calibration"]},
    {"question_text": "Describe your experience with blood banking and transfusion medicine.", "question_type": "technical", "difficulty": "medium", "expected_answer": "ABO/Rh typing, crossmatching, antibody screening, compatibility testing", "keywords": ["blood banking", "crossmatch", "transfusion"]},
    {"question_text": "What safety protocols do you follow when handling biological specimens?", "question_type": "domain_specific", "difficulty": "easy", "expected_answer": "Universal precautions, PPE, biosafety levels, waste disposal", "keywords": ["biosafety", "PPE", "specimen handling"]},
    {"question_text": "How do you ensure accuracy of patient specimen identification?", "question_type": "technical", "difficulty": "easy", "expected_answer": "Two-identifier verification, barcoding, chain of custody", "keywords": ["specimen identification", "verification", "barcoding"]},
    {"question_text": "Tell me about a time you identified an error in laboratory results.", "question_type": "behavioral", "difficulty": "medium", "expected_answer": "Detection, investigation, correction, preventive measures", "keywords": ["error detection", "quality assurance", "investigation"]},
    {"question_text": "Explain the difference between sensitivity and specificity in diagnostic testing.", "question_type": "technical", "difficulty": "medium", "expected_answer": "True positives/negatives, clinical significance, test selection", "keywords": ["sensitivity", "specificity", "diagnostics"]},
    {"question_text": "How do you maintain competency in rapidly evolving medical technology?", "question_type": "behavioral", "difficulty": "easy", "expected_answer": "Continuing education, certifications, vendor training, conferences", "keywords": ["competency", "continuing education", "technology"]},
    {"question_text": "Describe the regulatory requirements for clinical laboratories.", "question_type": "domain_specific", "difficulty": "medium", "expected_answer": "CLIA, CAP accreditation, state regulations, documentation requirements", "keywords": ["CLIA", "CAP", "accreditation", "regulations"]},
    {"question_text": "How would you handle a specimen that does not meet acceptance criteria?", "question_type": "situational", "difficulty": "medium", "expected_answer": "Rejection criteria, communication with collector, documentation, recollection", "keywords": ["specimen rejection", "criteria", "communication"]},
    {"question_text": "Explain the principle of flow cytometry and its clinical applications.", "question_type": "technical", "difficulty": "hard", "expected_answer": "Cell sorting, fluorescence, immunophenotyping, leukemia/lymphoma diagnosis", "keywords": ["flow cytometry", "immunophenotyping", "diagnostics"]},
    {"question_text": "What is your experience with point-of-care testing?", "question_type": "technical", "difficulty": "easy", "expected_answer": "POCT devices, correlation with lab results, QC, operator training", "keywords": ["POCT", "point-of-care", "rapid testing"]},
    {"question_text": "How do you approach method validation for a new laboratory test?", "question_type": "domain_specific", "difficulty": "hard", "expected_answer": "Accuracy, precision, linearity, reference range, comparison studies", "keywords": ["method validation", "accuracy", "precision"]},
    {"question_text": "Describe the importance of pre-analytical variables in laboratory testing.", "question_type": "technical", "difficulty": "medium", "expected_answer": "Patient preparation, collection, transport, processing effects on results", "keywords": ["pre-analytical", "specimen integrity", "variables"]},
    {"question_text": "How do you prioritize work when the laboratory is experiencing high volume?", "question_type": "situational", "difficulty": "medium", "expected_answer": "STAT orders first, systematic batching, communication, time management", "keywords": ["prioritization", "workflow", "STAT"]},
    {"question_text": "What measures do you take to prevent laboratory-acquired infections?", "question_type": "domain_specific", "difficulty": "medium", "expected_answer": "Standard precautions, BSC use, decontamination, spill procedures", "keywords": ["biosafety", "infection prevention", "decontamination"]},
    {"question_text": "Explain your understanding of hemoglobin electrophoresis.", "question_type": "technical", "difficulty": "hard", "expected_answer": "Hemoglobin variants, sickle cell, thalassemia, interpretation patterns", "keywords": ["hemoglobin", "electrophoresis", "hemoglobinopathy"]},
    {"question_text": "How do you handle equipment calibration and preventive maintenance?", "question_type": "technical", "difficulty": "medium", "expected_answer": "Calibration schedules, documentation, vendor PM, performance verification", "keywords": ["calibration", "maintenance", "documentation"]},
    {"question_text": "Describe a time when you had to work under pressure to deliver critical results.", "question_type": "behavioral", "difficulty": "medium", "expected_answer": "Time management, accuracy under pressure, communication, outcome", "keywords": ["pressure", "critical results", "time management"]},
    {"question_text": "What role does laboratory informatics play in modern healthcare?", "question_type": "domain_specific", "difficulty": "medium", "expected_answer": "LIS, data management, interfacing, reporting, decision support", "keywords": ["informatics", "LIS", "data management"]},
    {"question_text": "How do you perform and interpret a Gram stain?", "question_type": "technical", "difficulty": "easy", "expected_answer": "Staining procedure, morphology identification, clinical significance", "keywords": ["Gram stain", "microbiology", "morphology"]},
    {"question_text": "What is your experience with molecular diagnostics?", "question_type": "technical", "difficulty": "hard", "expected_answer": "PCR, sequencing, gene expression, infectious disease panels", "keywords": ["molecular diagnostics", "PCR", "genomics"]},
    {"question_text": "How do you communicate laboratory results effectively to clinical staff?", "question_type": "behavioral", "difficulty": "easy", "expected_answer": "Clear reporting, flagging abnormals, consultation, interpretation aids", "keywords": ["communication", "reporting", "clinical correlation"]}
  ]
}
